{
  "cate": "1",
  "date": "4æ10æ¥ 4æ14å",
  "datetime": "2018-04-10T04:14",
  "video": "/news/html/20180410/movie/k10011396891_201804100512_201804100534.html",
  "duration": 47,
  "img": "html/20180410/K10011396891_1804100512_1804100534_01_03.jpg",
  "title": "瀬戸大橋 四国と本州を結んで30年",
  "summary": "四国と本州を結ぶ瀬戸大橋が開通して、１０日で３０年を迎えました。これまでに橋を利用した自動車の数はおよそ１億７０００万台に上り、この３０年で地域の暮らしや経済に大きな変化をもたらしました。",
  "more": "香川県と岡山県を結ぶ瀬戸大橋は海峡部の橋の長さがおよそ１０キロの道路と鉄道の併用橋で、本州と四国を結ぶ３つのルートのうち最初のルートとして１兆１２００億円かけて建設され、昭和６３年４月１０日に開通しました。<br /><br />開通直後は車の通行量が当初の計画の半分にも達しませんでしたが、その後、通行料金の見直しの効果もあり、昨年度はおよそ８２２万台と３年連続で過去最高を更新し、開通から先月末まででおよそ１億７０００万台となりました。<br /><br />橋の開通は東京などの大消費地に農産物を鮮度のよい状態で運ぶことを可能にし、中でも香川県産のブロッコリーは東京都中央卸売市場への出荷量が去年５０００トン近くに上り、愛知県や北海道などの産地を抑えてトップとなりました。<br /><br />開通から１０日で３０年となる瀬戸大橋は物流の在り方を変えたほか交流人口を拡大し、四国と中国地方の暮らしと経済に大きな変化をもたらしました。",
  "body": [
    {
      "title": "",
      "img": "",
      "align": "",
      "text": "",
      "textPos": ""
    }
  ],
  "relationNews": [],
  "relationLink": [
    {
      "link": "http://www3.nhk.or.jp/lnews/takamatsu/",
      "title": "NHK高松放送局",
      "time": "各地のニュース",
      "datetime": ""
    }
  ],
  "word": [],
  "news_id": "k10011396891000",
  "yyyy": "2018",
  "mm": "04",
  "dd": "10",
  "url": "https://www3.nhk.or.jp/news/html/20180410/k10011396891000.html"
}