{
  "news_id": "k10011391291000",
  "news_prearranged_time": "2018-04-06 11:30:00",
  "title": "フィリピンの島　海をきれいにするため半年旅行できない",
  "title_with_ruby": "フィリピンの<ruby>島<rt>しま</rt></ruby>　<ruby>海<rt>うみ</rt></ruby>をきれいにするため<ruby>半年<rt>はんとし</rt></ruby><ruby>旅行<rt>りょこう</rt></ruby>できない",
  "outline_with_ruby": "<p>フィリピンのボラカイ<ruby>島<rt>とう</rt></ruby>は<ruby>美<rt>うつく</rt></ruby>しい<ruby>海岸<rt>かいがん</rt></ruby>が<ruby>有名<rt>ゆうめい</rt></ruby>な<ruby>島<rt>しま</rt></ruby>で、１<ruby>年<rt>ねん</rt></ruby>に２００<ruby>万<rt>まん</rt></ruby><ruby>人<rt>にん</rt></ruby>が<ruby>旅行<rt>りょこう</rt></ruby>に<ruby>来<rt>き</rt></ruby>ます。",
  "has_news_web_image": true,
  "has_news_web_movie": false,
  "has_news_easy_image": false,
  "has_news_easy_movie": false,
  "has_news_easy_voice": true,
  "news_web_image_uri": "https://www3.nhk.or.jp/news/html/20180405/../20180405/K10011391291_1804050908_1804050927_01_02.jpg",
  "news_web_movie_uri": "",
  "news_easy_image_uri": "''",
  "news_easy_movie_uri": "''",
  "news_easy_voice_uri": "k10011391291000.mp4",
  "url": "http://www3.nhk.or.jp/news/easy/k10011391291000/k10011391291000.html"
}